{
  "sections": {
    "image_banner": {
      "type": "image-banner",
      "blocks": {
        "heading": {
          "type": "heading",
          "settings": {
            "heading": "Hentze Family Farm"
          }
        },
        "2e6f8791-e355-48ef-9455-351e59d11056": {
          "type": "text",
          "settings": {
            "text": "<p>Century Family Farm in Junction City<\/p>"
          }
        }
      },
      "block_order": [
        "heading",
        "2e6f8791-e355-48ef-9455-351e59d11056"
      ],
      "settings": {
        "image": "shopify:\/\/shop_images\/small-family-tends-to-their-cows.jpg"
      }
    },
    "16275876157298bbfc": {
      "type": "rich-text",
      "blocks": {
        "16275876157298bbfc-0": {
          "type": "heading",
          "settings": {
            "heading": "Our Story"
          }
        },
        "16275876157298bbfc-1": {
          "type": "text",
          "settings": {
            "text": "<p>A small family farm in the South Willamette Valley established in 1902. Currently the fifth generation has joined the farm to try and revitalize and steward the farm. There is a produce stand and a small cook shack on the farm. Over the season we have a few events, our Cherry Festival, and OctoberFest - a celebration of Fall Harvest with a U-Pick Pumpkin Patch. <br\/><br\/><a href=\"\/pages\/about-us\" title=\"About Us\"><em>Read More<\/em><\/a><\/p>"
          }
        }
      },
      "block_order": [
        "16275876157298bbfc-0",
        "16275876157298bbfc-1"
      ],
      "settings": {
      }
    },
    "featured_products": {
      "type": "featured-collection",
      "settings": {
        "title": "Featured products",
        "collection": "",
        "products_to_show": 4,
        "show_view_all": true,
        "swipe_on_mobile": false,
        "image_ratio": "adapt",
        "show_secondary_image": false,
        "add_image_padding": false,
        "show_vendor": false
      }
    },
    "16276299100ebb3c7f": {
      "type": "image-banner",
      "blocks": {
        "16276299100ebb3c7f-0": {
          "type": "heading",
          "settings": {
            "heading": "Celebrate"
          }
        },
        "16276299100ebb3c7f-1": {
          "type": "text",
          "settings": {
            "text": "<p>Farm Events<\/p><p><\/p><p><a href=\"\/pages\/events\" title=\"Events\"><strong>More Information<\/strong><\/a><\/p>"
          }
        }
      },
      "block_order": [
        "16276299100ebb3c7f-0",
        "16276299100ebb3c7f-1"
      ],
      "settings": {
        "image": "shopify:\/\/shop_images\/outdoor-dessert-table-filled-with-cakes-and-macarons.jpg"
      }
    }
  },
  "order": [
    "image_banner",
    "16275876157298bbfc",
    "featured_products",
    "16276299100ebb3c7f"
  ]
}
